quectelatcommands/__init__.py
quectelatcommands/quectelGnssATCommands.py
quectelatcommands/quectelModemATCommands.py
quectelatcommands/quectelSerial.py
quectelatcommands-1.0.19.dist-info/LICENSE
quectelatcommands-1.0.19.dist-info/METADATA
quectelatcommands-1.0.19.dist-info/WHEEL
quectelatcommands-1.0.19.dist-info/entry_points.txt
quectelatcommands-1.0.19.dist-info/top_level.txt
quectelatcommands-1.0.19.dist-info/RECORD
