Metadata-Version: 2.1
Name: quectelatcommands
Version: 1.0.19
Summary: A Python package for Quectel AT Commands
Author: Pierre Godicheau
Author-email: Pierre Godicheau <pgodicheau@scheiber.com>
License: GNU General Public License v3.0
Project-URL: Homepage, https://github.com/scheiber-sa/quectel-at-commands
Project-URL: Documentation, https://quectel-at-commands.readthedocs.io
Project-URL: Bug-Tracker, https://github.com/scheiber-sa/quectel-at-commands/issues
Classifier: Programming Language :: Python :: 3
Classifier: License :: OSI Approved :: GNU General Public License v3 (GPLv3)
Classifier: Operating System :: OS Independent
Requires-Python: >=3.7
License-File: LICENSE
Requires-Dist: pyserial>=3.4
Requires-Dist: click>=8.1.7
Provides-Extra: docs
Requires-Dist: Sphinx>=5.1.1; extra == "docs"
Requires-Dist: sphinx-rtd-theme>=1.0.0; extra == "docs"
Requires-Dist: tomli>=2.0.1; extra == "docs"
Provides-Extra: lint
Requires-Dist: black<25.0,>=24.3; extra == "lint"
Requires-Dist: flake8>=5.0.0; extra == "lint"
Requires-Dist: isort>=5.13.2; extra == "lint"
Provides-Extra: test
Requires-Dist: pytest>=8.2.1; extra == "test"
Requires-Dist: pytest-asyncio>=0.23.7; extra == "test"
Requires-Dist: pytest-cov>=3.0.0; extra == "test"
